{"version":"1.0","chainId":42161,"createdAt":1699446823375,"meta":{"name":"Transactions Batch","description":"","txBuilderVersion":"1.16.2","createdFromSafeAddress":"0x5cBb2167677c2259F421457542f6E5A805B1FF2F","createdFromOwnerAddress":"","checksum":""},"transactions":[{"to":"0xa44dF8A8581C2cb536234E6640112fFf932ED2c4","value":"0","data":null,"contractMethod":{"inputs":[{"internalType":"address","name":"target","type":"address"},{"internalType":"uint256","name":"value","type":"uint256"},{"internalType":"bytes","name":"data","type":"bytes"},{"internalType":"bytes32","name":"predecessor","type":"bytes32"},{"internalType":"bytes32","name":"salt","type":"bytes32"},{"internalType":"uint256","name":"delay","type":"uint256"}],"name":"schedule","payable":false},"contractInputsValues":{"target":"0xbb5ea28ec8044E3ce55c459C47EEDed8c6CB685f","value":"0","data":"0xa4bb42a10000000000000000000000003ca375b8107cb2c7f520ca87b2def8dc5040aeb4","predecessor":"0x0000000000000000000000000000000000000000000000000000000000000000","salt":"0x0000000000000000000000000000000000000000000000000000000000000000","delay":"21600"}}]}