{"version":"1.0","chainId":8453,"createdAt":1738856668458,"meta":{"name":"Transactions Batch","description":"","txBuilderVersion":"1.16.2","createdFromSafeAddress":"0xAba227eAd919E060B95B02bab2270646840bF9bC","createdFromOwnerAddress":"","checksum":""},"transactions":[{"to":"0x8ab9012D1BfF1b62c2ad82AE0106593371e6b247","value":"0","data":null,"contractMethod":{"inputs":[{"internalType":"address","name":"target","type":"address"},{"internalType":"uint256","name":"value","type":"uint256"},{"internalType":"bytes","name":"data","type":"bytes"},{"internalType":"bytes32","name":"predecessor","type":"bytes32"},{"internalType":"bytes32","name":"salt","type":"bytes32"},{"internalType":"uint256","name":"delay","type":"uint256"}],"name":"schedule","payable":false},"contractInputsValues":{"target":"0x86f79d8cE9a5089f196A1e81ced37e22D4721313","value":"0","data":"0x3659cfe6000000000000000000000000d285cda17be51841d957db3ea30c0b882e7b7b1a","predecessor":"0x0000000000000000000000000000000000000000000000000000000000000000","salt":"0x0d8c86852f3f89f32e2ae651f5722cf7f121c7b6db2f13b7848fc0a9691e432c","delay":"86400"}}]}